<customrecordtype scriptid="customrecord_ts_ec_tipo_transaccion">
  <accesstype>CUSTRECORDENTRYPERM</accesstype>
  <allowattachments>F</allowattachments>
  <allowinlinedeleting>T</allowinlinedeleting>
  <allowinlinedetaching>T</allowinlinedetaching>
  <allowinlineediting>T</allowinlineediting>
  <allowmobileaccess>F</allowmobileaccess>
  <allownumberingoverride>F</allownumberingoverride>
  <allowquickadd>F</allowquickadd>
  <allowquicksearch>F</allowquicksearch>
  <allowuiaccess>T</allowuiaccess>
  <customsegment></customsegment>
  <description>Esta lista muestra los Tipos de transacción asignados a la subsidiaria seleccionada. Todos los Países.</description>
  <enabledle>F</enabledle>
  <enablekeywords>F</enablekeywords>
  <enablemailmerge>F</enablemailmerge>
  <enablenametranslation>F</enablenametranslation>
  <enablenumbering>F</enablenumbering>
  <enableoptimisticlocking>F</enableoptimisticlocking>
  <enablesystemnotes>T</enablesystemnotes>
  <hierarchical>F</hierarchical>
  <icon></icon>
  <iconbuiltin>T</iconbuiltin>
  <iconindex></iconindex>
  <includeinsearchmenu>F</includeinsearchmenu>
  <includename>T</includename>
  <isinactive>F</isinactive>
  <isordered>F</isordered>
  <numberinginit></numberinginit>
  <numberingmindigits></numberingmindigits>
  <numberingprefix></numberingprefix>
  <numberingsuffix></numberingsuffix>
  <recordname>EC - TIPO DE TRANSACCION</recordname>
  <showcreationdate>F</showcreationdate>
  <showcreationdateonlist>F</showcreationdateonlist>
  <showid>F</showid>
  <showlastmodified>F</showlastmodified>
  <showlastmodifiedonlist>F</showlastmodifiedonlist>
  <shownotes>T</shownotes>
  <showowner>F</showowner>
  <showownerallowchange>F</showownerallowchange>
  <showowneronlist>F</showowneronlist>
  <customrecordcustomfields>
    <customrecordcustomfield scriptid="custrecord_ts_ec_pais">
      <accesslevel>2</accesslevel>
      <allowquickadd>F</allowquickadd>
      <applyformatting>F</applyformatting>
      <checkspelling>F</checkspelling>
      <defaultchecked>F</defaultchecked>
      <defaultselection></defaultselection>
      <defaultvalue></defaultvalue>
      <description></description>
      <displayheight></displayheight>
      <displaytype>NORMAL</displaytype>
      <displaywidth></displaywidth>
      <dynamicdefault></dynamicdefault>
      <encryptatrest>F</encryptatrest>
      <fieldtype>SELECT</fieldtype>
      <globalsearch>F</globalsearch>
      <help></help>
      <isformula>F</isformula>
      <ismandatory>F</ismandatory>
      <isparent>F</isparent>
      <label>País</label>
      <linktext></linktext>
      <maxlength></maxlength>
      <maxvalue></maxvalue>
      <minvalue></minvalue>
      <onparentdelete>NO_ACTION</onparentdelete>
      <parentsubtab></parentsubtab>
      <rolerestrict>F</rolerestrict>
      <searchcomparefield></searchcomparefield>
      <searchdefault></searchdefault>
      <searchlevel>2</searchlevel>
      <selectrecordtype>-159</selectrecordtype>
      <showinlist>T</showinlist>
      <sourcefilterby></sourcefilterby>
      <sourcefrom></sourcefrom>
      <sourcelist></sourcelist>
      <storevalue>T</storevalue>
      <subtab></subtab>
    </customrecordcustomfield>
    <customrecordcustomfield scriptid="custrecord_ts_ec_tipo_transacc">
      <accesslevel>2</accesslevel>
      <allowquickadd>F</allowquickadd>
      <applyformatting>F</applyformatting>
      <checkspelling>F</checkspelling>
      <defaultchecked>F</defaultchecked>
      <defaultselection></defaultselection>
      <defaultvalue></defaultvalue>
      <description></description>
      <displayheight></displayheight>
      <displaytype>NORMAL</displaytype>
      <displaywidth></displaywidth>
      <dynamicdefault></dynamicdefault>
      <encryptatrest>F</encryptatrest>
      <fieldtype>SELECT</fieldtype>
      <globalsearch>F</globalsearch>
      <help></help>
      <isformula>F</isformula>
      <ismandatory>F</ismandatory>
      <isparent>F</isparent>
      <label>EC - TIPO DE TRANSACCION</label>
      <linktext></linktext>
      <maxlength></maxlength>
      <maxvalue></maxvalue>
      <minvalue></minvalue>
      <onparentdelete>NO_ACTION</onparentdelete>
      <parentsubtab></parentsubtab>
      <rolerestrict>F</rolerestrict>
      <searchcomparefield></searchcomparefield>
      <searchdefault></searchdefault>
      <searchlevel>2</searchlevel>
      <selectrecordtype>[scriptid=customrecord_evol_ts_ec_setup_trans_typ]</selectrecordtype>
      <showinlist>F</showinlist>
      <sourcefilterby></sourcefilterby>
      <sourcefrom></sourcefrom>
      <sourcelist></sourcelist>
      <storevalue>T</storevalue>
      <subtab></subtab>
    </customrecordcustomfield>
    <customrecordcustomfield scriptid="custrecord_ts_ec_campo">
      <accesslevel>2</accesslevel>
      <allowquickadd>F</allowquickadd>
      <applyformatting>F</applyformatting>
      <checkspelling>F</checkspelling>
      <defaultchecked>F</defaultchecked>
      <defaultselection></defaultselection>
      <defaultvalue></defaultvalue>
      <description></description>
      <displayheight></displayheight>
      <displaytype>NORMAL</displaytype>
      <displaywidth></displaywidth>
      <dynamicdefault></dynamicdefault>
      <encryptatrest>F</encryptatrest>
      <fieldtype>TEXT</fieldtype>
      <globalsearch>F</globalsearch>
      <help></help>
      <isformula>F</isformula>
      <ismandatory>F</ismandatory>
      <isparent>F</isparent>
      <label>EC - CAMPO</label>
      <linktext></linktext>
      <maxlength></maxlength>
      <maxvalue></maxvalue>
      <minvalue></minvalue>
      <onparentdelete></onparentdelete>
      <parentsubtab></parentsubtab>
      <rolerestrict>F</rolerestrict>
      <searchcomparefield></searchcomparefield>
      <searchdefault></searchdefault>
      <searchlevel>2</searchlevel>
      <selectrecordtype></selectrecordtype>
      <showinlist>T</showinlist>
      <sourcefilterby></sourcefilterby>
      <sourcefrom></sourcefrom>
      <sourcelist></sourcelist>
      <storevalue>T</storevalue>
      <subtab></subtab>
    </customrecordcustomfield>
  </customrecordcustomfields>
  <instances>
    <instance scriptid="val_752897_7451241_sb1_250">
      <custrecord_ts_ec_campo>07</custrecord_ts_ec_campo>
      <custrecord_ts_ec_pais>63</custrecord_ts_ec_pais>
      <custrecord_ts_ec_tipo_transacc>[scriptid=customrecord_evol_ts_ec_setup_trans_typ.val_752842_7451241_sb1_930]</custrecord_ts_ec_tipo_transacc>
      <isinactive>F</isinactive>
      <name>COMPROBANTE DE RETENCION</name>
    </instance>
  </instances>
  <permissions>
    <permission>
      <permittedlevel>FULL</permittedlevel>
      <permittedrole>[scriptid=customrole1212]</permittedrole>
      <restriction></restriction>
    </permission>
  </permissions>
</customrecordtype>